risc/.mypy_cache/3.8/@plugins_snapshot.json
risc/.mypy_cache/3.8/_ast.data.json
risc/.mypy_cache/3.8/_ast.meta.json
risc/.mypy_cache/3.8/_importlib_modulespec.data.json
risc/.mypy_cache/3.8/_importlib_modulespec.meta.json
risc/.mypy_cache/3.8/abc.data.json
risc/.mypy_cache/3.8/abc.meta.json
risc/.mypy_cache/3.8/ast.data.json
risc/.mypy_cache/3.8/ast.meta.json
risc/.mypy_cache/3.8/builtins.data.json
risc/.mypy_cache/3.8/builtins.meta.json
risc/.mypy_cache/3.8/codecs.data.json
risc/.mypy_cache/3.8/codecs.meta.json
risc/.mypy_cache/3.8/collections/__init__.data.json
risc/.mypy_cache/3.8/collections/__init__.meta.json
risc/.mypy_cache/3.8/collections/abc.data.json
risc/.mypy_cache/3.8/collections/abc.meta.json
risc/.mypy_cache/3.8/dataclasses.data.json
risc/.mypy_cache/3.8/dataclasses.meta.json
risc/.mypy_cache/3.8/datetime.data.json
risc/.mypy_cache/3.8/datetime.meta.json
risc/.mypy_cache/3.8/email/__init__.data.json
risc/.mypy_cache/3.8/email/__init__.meta.json
risc/.mypy_cache/3.8/email/charset.data.json
risc/.mypy_cache/3.8/email/charset.meta.json
risc/.mypy_cache/3.8/email/contentmanager.data.json
risc/.mypy_cache/3.8/email/contentmanager.meta.json
risc/.mypy_cache/3.8/email/errors.data.json
risc/.mypy_cache/3.8/email/errors.meta.json
risc/.mypy_cache/3.8/email/header.data.json
risc/.mypy_cache/3.8/email/header.meta.json
risc/.mypy_cache/3.8/email/message.data.json
risc/.mypy_cache/3.8/email/message.meta.json
risc/.mypy_cache/3.8/email/policy.data.json
risc/.mypy_cache/3.8/email/policy.meta.json
risc/.mypy_cache/3.8/enum.data.json
risc/.mypy_cache/3.8/enum.meta.json
risc/.mypy_cache/3.8/hashlib.data.json
risc/.mypy_cache/3.8/hashlib.meta.json
risc/.mypy_cache/3.8/http/__init__.data.json
risc/.mypy_cache/3.8/http/__init__.meta.json
risc/.mypy_cache/3.8/http/client.data.json
risc/.mypy_cache/3.8/http/client.meta.json
risc/.mypy_cache/3.8/http/cookiejar.data.json
risc/.mypy_cache/3.8/http/cookiejar.meta.json
risc/.mypy_cache/3.8/importlib/__init__.data.json
risc-0.2.1.dist-info/entry_points.txt
risc-0.2.1.dist-info/WHEEL
risc-0.2.1.dist-info/METADATA
risc-0.2.1.dist-info/RECORD
